idesyde/__init__.py
idesyde/__main__.py
idesyde/cli.py
idesyde/exploration.py
idesyde/identification/__init__.py
idesyde/identification/api.py
idesyde/identification/interfaces.py
idesyde/identification/models.py
idesyde/identification/rules.py
idesyde/interfaces.py
idesyde/math.py
idesyde/minizinc/__init__.py
idesyde/minizinc/dependent_job_scheduling.mzn
idesyde/minizinc/period_tasks_basic_model.mzn
idesyde/minizinc/period_tasks_basic_model_test1.dzn
idesyde/minizinc/sdf_basic_model.mzn
idesyde/minizinc/sdf_df_model.mzn
idesyde/minizinc/sdf_df_test.dzn
idesyde/minizinc/sdf_job_scheduling.mzn
idesyde/minizinc/sdf_linear_dmodel.mzn
idesyde/minizinc/sdf_linear_dmodel_test.dzn
idesyde/minizinc/sdf_mpsoc_linear_cluster.mzn
idesyde/minizinc/sdf_mpsoc_linear_dmodel.mzn
idesyde/minizinc/sdf_order_linear_dmodel.mzn
idesyde/minizinc/sdf_order_linear_dmodel_test.dzn
idesyde/minizinc/sdf_test_data.dzn
idesyde/sdf.py
idesyde-0.1.14.dist-info/entry_points.txt
idesyde-0.1.14.dist-info/WHEEL
idesyde-0.1.14.dist-info/METADATA
idesyde-0.1.14.dist-info/RECORD
